LICENSE
MANIFEST.in
README.rst
setup.py
PyVCF3.egg-info/PKG-INFO
PyVCF3.egg-info/SOURCES.txt
PyVCF3.egg-info/dependency_links.txt
PyVCF3.egg-info/entry_points.txt
PyVCF3.egg-info/requires.txt
PyVCF3.egg-info/top_level.txt
scripts/vcf_filter.py
scripts/vcf_melt
scripts/vcf_sample_filter.py
vcf/__init__.py
vcf/bgzf.py
vcf/cparse.pyx
vcf/filters.py
vcf/model.py
vcf/parser.py
vcf/sample_filter.py
vcf/utils.py
vcf/test/1kg.sites.vcf
vcf/test/1kg.vcf.gz
vcf/test/FT.vcf
vcf/test/__init__.py
vcf/test/bad-info-character.vcf
vcf/test/bcftools.vcf
vcf/test/contig_idonly.vcf
vcf/test/example-4.0.vcf
vcf/test/example-4.1-bnd.vcf
vcf/test/example-4.1-info-multiple-values.vcf
vcf/test/example-4.1-ploidy.vcf
vcf/test/example-4.1-sv.vcf
vcf/test/example-4.1.vcf
vcf/test/example-4.2.vcf
vcf/test/freebayes.vcf
vcf/test/gatk.vcf
vcf/test/gatk_26_meta.vcf
vcf/test/gonl.chr20.release4.gtc.vcf
vcf/test/info-type-character.vcf
vcf/test/issue-140-file1.vcf
vcf/test/issue-140-file2.vcf
vcf/test/issue-140-file3.vcf
vcf/test/issue-16.vcf
vcf/test/issue-201.vcf.gz
vcf/test/issue-201.vcf.gz.tbi
vcf/test/issue-214.vcf
vcf/test/issue-254.vcf
vcf/test/issue_49.vcf
vcf/test/metadata-whitespace.vcf
vcf/test/mixed-filtering.vcf
vcf/test/null_genotype_mono.vcf
vcf/test/parse-meta-line.vcf
vcf/test/prof.py
vcf/test/samples-space.vcf
vcf/test/samtools.vcf
vcf/test/strelka.vcf
vcf/test/string_as_flag.vcf
vcf/test/tb.vcf.gz
vcf/test/tb.vcf.gz.tbi
vcf/test/test_vcf.py
vcf/test/uncalled_genotypes.vcf
vcf/test/walk_left.vcf
vcf/test/walk_refcall.vcf